htec_drf_dx_datagrid/__init__.py
htec_drf_dx_datagrid/exceptions.py
htec_drf_dx_datagrid/filters.py
htec_drf_dx_datagrid/mixins.py
htec_drf_dx_datagrid/pagination.py
htec_drf_dx_datagrid/summary.py
htec_drf_dx_datagrid/viewsets.py
tests/__init__.py
tests/test_filters.py
htec_drf_dx_datagrid-0.5.6.dist-info/LICENSE
htec_drf_dx_datagrid-0.5.6.dist-info/METADATA
htec_drf_dx_datagrid-0.5.6.dist-info/WHEEL
htec_drf_dx_datagrid-0.5.6.dist-info/top_level.txt
htec_drf_dx_datagrid-0.5.6.dist-info/RECORD
