Metadata-Version: 2.1
Name: htec_drf_dx_datagrid
Version: 0.5.6
Summary: This package provides easy integration between Django REST framework and DevExtreme Data Grid. It handles grouping, paging, filtering, aggregating and ordering on serverside.
Home-page: https://github.com/sbarroso86/htec-drf-dx-datagrid
Author: SergeyMatveev88
Author-email: dazranagon@yandex.ru
License: MIT
Classifier: Programming Language :: Python :: 3
Classifier: License :: OSI Approved :: MIT License
Classifier: Operating System :: OS Independent
Classifier: Framework :: Django
Requires-Python: >=3.5
License-File: LICENSE
Requires-Dist: djangorestframework
